candidate_test.v
//На вход модуля поступают тактовые импульсы clk_i c частотой N, асинхронный сигнал сброса reset_n_i (сброс по уровню 0).
//В произвольный момент времени могут приходить асинхронные импульсы syncro_i длительностью не менее одного такта сигнала clk_i.
//От переднего фронта этого импульса необходимо отсчитать 11 тактов clk_i и провести 8 измерений с помощью АЦП.
//Для выборки данных на АЦП необходимо подать сигнал запроса adc_data_req_o длительностью не менее 2 тактов clk_i. По переднему фронту
//этого сигнала запроса АЦП начинает выборку и оцифровку данных. АЦП работает по фронту запроса, а не по уровню. Необходимо снять сигнал запроса и дождаться готовности данных АЦП по сигналу data_rdy_o.
//На это потребуется несколько тактов clk_i. Данные с АЦП будут готовы по переднему фронту data_rdy_o и будут актуальны до следующиго запроса.
//Сигнал data_rdy_o при этом будет в состоянии логической 1. Значения с АЦП двуполярные в дополнительном коде.
//Их необходимо усреднить по полученным 8-ми измерениям и в таком же формате, как выдаёт АЦП выдать на выход с флагом готовности data_rdy_o. 
//
//Код оформить на языке Verilog HDL без использования конструкций SystemVerilog
//Проверяться проект будет в среде  в Icarus Verilog версии 11



`define PAUSE_AFTER_SYNCRO 	11 		// in clk period
`define NUM_OF_ADC_DATA 	8 		// number of ADC data for accumulate (don't edit without code editing)

module data_acquire(
	input clk_i,
	input reset_n_i,
	
//ADC interface
	output	adc_data_req_o,
	input	adc_data_rdy_i,
	input [11:0] adc_data_i,
	
//Module output interface
	input			syncro_i,
	output [11:0]	data_o,
	output 			data_rdy_o
);
	
	wire signed [11:0] 	adc_data_i;
	wire signed	[11:0] 	data_o;
	

	// detecting posedge of syncro_i:
	reg r_syncro_i;
	always @ (posedge clk_i or negedge reset_n_i) begin
		if (~reset_n_i) r_syncro_i <= 1'b0;
		else r_syncro_i <= syncro_i;
	end
	wire syncro_i_posedge = ({r_syncro_i, syncro_i} == 2'b01);

	`define 	STATE_IDLE 				2'd0
	`define 	STATE_PAUSE 			2'd1
	`define 	STATE_WAIT_ADC_START 	2'd2
	`define 	STATE_WAIT_ADC_READY 	2'd3
	
	reg 		[1:0] 	state;
	reg 		[3:0] 	syscnt;
	reg 				adc_data_req_o;
	reg signed [14:0] 	adc_data_acc;
	reg 				data_rdy_o;
	
	always @ (posedge clk_i or negedge reset_n_i) begin
		if (~reset_n_i) begin
			state 			<= `STATE_IDLE;
			adc_data_req_o 	<= 0;
			data_rdy_o 		<= 0;
		end else begin
			
			case (state)
				
				`STATE_IDLE: begin
					if (syncro_i_posedge) begin
						syscnt 	<= 4'd0;
						state 	<= `STATE_PAUSE;
					end
				end
				
				`STATE_PAUSE: begin
					if (syscnt != (`PAUSE_AFTER_SYNCRO-1)) begin
						syscnt 	<= syscnt + 4'd1;
					end else begin
						adc_data_req_o 	<= 1'b1;
						data_rdy_o 		<= 1'b0;
						adc_data_acc 	<= 0;
						if (adc_data_req_o) begin 
							syscnt 			<= 4'd0;
							state 			<= `STATE_WAIT_ADC_START;
						end
					end
				end
				
				`STATE_WAIT_ADC_START: begin
					if (~adc_data_rdy_i) begin
						adc_data_req_o 	<= 1'b0;
						state 			<= `STATE_WAIT_ADC_READY;
					end
				end
				
				`STATE_WAIT_ADC_READY: begin
					if (adc_data_rdy_i) begin
						adc_data_acc 	<= adc_data_acc + adc_data_i;
						syscnt 			<= syscnt + 4'd1;
						if (syscnt != (`NUM_OF_ADC_DATA-1)) begin
							adc_data_req_o 	<= 1'b1;
							state 			<= `STATE_WAIT_ADC_START;
						end else begin
							data_rdy_o 		<= 1'b1;
							state 			<= `STATE_IDLE;
						end
					end
				end
				
			endcase
			
		end
			
	end
	
	assign data_o = adc_data_acc[14:3];

endmodule

tb.v
`timescale 1ns/100ps 

// user preferences:
`define N 				10000000 	// clk frequency, Hz
`define DUMPFILENAME 	"test.vcd" 	// name of VCD file for GTKWave

// testbench module:
module testbench;
	
	// parameters (don't edit):
	localparam CLK_PERIOD_HALF 	= (10**9)/`N;
	localparam CLK_PERIOD 		= CLK_PERIOD_HALF * 2;
	
	// for waveforms:
	initial begin
		$dumpfile(`DUMPFILENAME);
		$dumpvars(0,data_acquire_0);
	end
	
	// clk signal:
	reg clk = 0;
	always #(CLK_PERIOD_HALF) clk <= ~clk;
	
	// testing procedure:
	reg 					reset_n = 0;
	reg 					syncro 	= 0;
	wire 					data_rdy_o;
	wire signed [11:0] 		data_o;
	reg 		[12*8-1:0] 	adc_data_8;
	reg 		[11:0] 		data_right_answer;
	
	initial begin 
		
		// on:
		#(CLK_PERIOD*10) reset_n <= 1'b1;
		
		// Tests:
		#(CLK_PERIOD*10 + 15) test({12'd8, 12'd7, 12'd6, 12'd5, 12'd4, 12'd3, 12'd2, 12'd1});
		#(CLK_PERIOD*10 + 25) test(-1);
		#(CLK_PERIOD*10 + 25) test({12'd3, 12'd12, -12'sd77, 12'd0, 12'd222, 12'd4, 12'd65, 12'd92});
		#(CLK_PERIOD*10 + 25) test({12'd35, 12'd350, -12'sd911, 12'd28, 12'd287, -12'd1478, -12'd979, -12'd584});
		#(CLK_PERIOD*10 + 25) test({-12'sd914, -12'sd1859, -12'sd1650, 12'd1325, 12'd798, -12'sd749, 12'd1844, -12'd1907});
		
		
		// finish:
		#(CLK_PERIOD*50) $finish;

		
	end
	

	// test's tasks:
	task test;
		input [12*8-1:0] adc_data_in;
		reg signed [14:0] dt_right_ans;
		integer i;
		begin
			dt_right_ans = 0;
			for (i=0; i < 8; i=i+1) begin
				$display("adc_data_in[%d] = %d", i[2:0], $signed(adc_data_in[i*12 +: 12]));
				dt_right_ans = dt_right_ans + $signed(adc_data_in[i*12 +: 12]);
			end
			dt_right_ans = dt_right_ans >>> 3;
			
			adc_data_8 <= adc_data_in;

			syncro 		<= 1'b1;
			#(CLK_PERIOD*5) syncro <= 1'b0;
			
			@ (posedge data_rdy_o);
			if (data_o == dt_right_ans[11:0]) begin
				$display("passed (dt_right_ans == data_o == %d)\n", data_o);
			end else begin
				$display("not passed, dt_right_ans = %d, data_o = %d\n", dt_right_ans, data_o);
			end
			
		end
	endtask


	// ADC model:
	wire 		adc_data_req;
	reg 		adc_data_rdy = 1'b0;
	reg [11:0] 	adc_data;
	
	
	always begin
		@(posedge adc_data_req) #(CLK_PERIOD*(5-1));
		@(posedge clk) adc_data_rdy <= 1'b0;
		@(posedge clk) #(CLK_PERIOD*(15-1));
		@(posedge clk);
		adc_data_rdy 	<= 1'b1;
		adc_data 		<= adc_data_8[11:0];
		adc_data_8 		<= {12'dx, adc_data_8[12*8-1:12]};
	end
				
	
	
	// DUT:
	data_acquire data_acquire_0 (
	
		.clk_i		(clk),
		.reset_n_i 	(reset_n),
		
		//ADC interface
		.adc_data_req_o(adc_data_req),
		.adc_data_rdy_i(adc_data_rdy),
		.adc_data_i(adc_data),
		
		//Module output interface
		.syncro_i(syncro),
		.data_o(data_o),
		.data_rdy_o(data_rdy_o)
	
	);

endmodule

test.vcd
$date
	Mon Nov 07 18:59:14 2022
$end
$version
	Icarus Verilog
$end
$timescale
	100ps
$end
$scope module testbench $end
$scope module data_acquire_0 $end
$var wire 12 ! adc_data_i [11:0] $end
$var wire 1 " adc_data_rdy_i $end
$var wire 1 # clk_i $end
$var wire 1 $ reset_n_i $end
$var wire 1 % syncro_i $end
$var wire 1 & syncro_i_posedge $end
$var wire 12 ' data_o [11:0] $end
$var reg 15 ( adc_data_acc [14:0] $end
$var reg 1 ) adc_data_req_o $end
$var reg 1 * data_rdy_o $end
$var reg 1 + r_syncro_i $end
$var reg 2 , state [1:0] $end
$var reg 4 - syscnt [3:0] $end
$upscope $end
$upscope $end
$enddefinitions $end
$comment Show the parameter values. $end
$dumpall
$end
#0
$dumpvars
bx -
b0 ,
0+
0*
0)
bx (
bx '
0&
0%
0$
0#
0"
bx !
$end
#1000
1#
#2000
0#
#3000
1#
#4000
0#
#5000
1#
#6000
0#
#7000
1#
#8000
0#
#9000
1#
#10000
0#
#11000
1#
#12000
0#
#13000
1#
#14000
0#
#15000
1#
#16000
0#
#17000
1#
#18000
0#
#19000
1#
#20000
0#
1$
#21000
1#
#22000
0#
#23000
1#
#24000
0#
#25000
1#
#26000
0#
#27000
1#
#28000
0#
#29000
1#
#30000
0#
#31000
1#
#32000
0#
#33000
1#
#34000
0#
#35000
1#
#36000
0#
#37000
1#
#38000
0#
#39000
1#
#40000
0#
#40150
1&
1%
#41000
b1 ,
b0 -
0&
1+
1#
#42000
0#
#43000
b1 -
1#
#44000
0#
#45000
b10 -
1#
#46000
0#
#47000
b11 -
1#
#48000
0#
#49000
b100 -
1#
#50000
0#
#50150
0%
#51000
0+
b101 -
1#
#52000
0#
#53000
b110 -
1#
#54000
0#
#55000
b111 -
1#
#56000
0#
#57000
b1000 -
1#
#58000
0#
#59000
b1001 -
1#
#60000
0#
#61000
b1010 -
1#
#62000
0#
#63000
b0 '
b0 (
1)
1#
#64000
0#
#65000
b10 ,
b0 -
1#
#66000
0#
#67000
b11 ,
0)
1#
#68000
0#
#69000
1#
#70000
0#
#71000
1#
#72000
0#
#73000
1#
#74000
0#
#75000
1#
#76000
0#
#77000
1#
#78000
0#
#79000
1#
#80000
0#
#81000
1#
#82000
0#
#83000
1#
#84000
0#
#85000
1#
#86000
0#
#87000
1#
#88000
0#
#89000
1#
#90000
0#
#91000
1#
#92000
0#
#93000
1#
#94000
0#
#95000
1#
#96000
0#
#97000
1#
#98000
0#
#99000
1#
#100000
0#
#101000
b1 !
1"
1#
#102000
0#
#103000
b10 ,
1)
b1 -
b1 (
1#
#104000
0#
#105000
1#
#106000
0#
#107000
1#
#108000
0#
#109000
1#
#110000
0#
#111000
0"
1#
#112000
0#
#113000
b11 ,
0)
1#
#114000
0#
#115000
1#
#116000
0#
#117000
1#
#118000
0#
#119000
1#
#120000
0#
#121000
1#
#122000
0#
#123000
1#
#124000
0#
#125000
1#
#126000
0#
#127000
1#
#128000
0#
#129000
1#
#130000
0#
#131000
1#
#132000
0#
#133000
1#
#134000
0#
#135000
1#
#136000
0#
#137000
1#
#138000
0#
#139000
1#
#140000
0#
#141000
b10 !
1"
1#
#142000
0#
#143000
b10 ,
1)
b10 -
b11 (
1#
#144000
0#
#145000
1#
#146000
0#
#147000
1#
#148000
0#
#149000
1#
#150000
0#
#151000
0"
1#
#152000
0#
#153000
b11 ,
0)
1#
#154000
0#
#155000
1#
#156000
0#
#157000
1#
#158000
0#
#159000
1#
#160000
0#
#161000
1#
#162000
0#
#163000
1#
#164000
0#
#165000
1#
#166000
0#
#167000
1#
#168000
0#
#169000
1#
#170000
0#
#171000
1#
#172000
0#
#173000
1#
#174000
0#
#175000
1#
#176000
0#
#177000
1#
#178000
0#
#179000
1#
#180000
0#
#181000
b11 !
1"
1#
#182000
0#
#183000
b10 ,
1)
b11 -
b110 (
1#
#184000
0#
#185000
1#
#186000
0#
#187000
1#
#188000
0#
#189000
1#
#190000
0#
#191000
0"
1#
#192000
0#
#193000
b11 ,
0)
1#
#194000
0#
#195000
1#
#196000
0#
#197000
1#
#198000
0#
#199000
1#
#200000
0#
#201000
1#
#202000
0#
#203000
1#
#204000
0#
#205000
1#
#206000
0#
#207000
1#
#208000
0#
#209000
1#
#210000
0#
#211000
1#
#212000
0#
#213000
1#
#214000
0#
#215000
1#
#216000
0#
#217000
1#
#218000
0#
#219000
1#
#220000
0#
#221000
b100 !
1"
1#
#222000
0#
#223000
b1 '
b10 ,
1)
b100 -
b1010 (
1#
#224000
0#
#225000
1#
#226000
0#
#227000
1#
#228000
0#
#229000
1#
#230000
0#
#231000
0"
1#
#232000
0#
#233000
b11 ,
0)
1#
#234000
0#
#235000
1#
#236000
0#
#237000
1#
#238000
0#
#239000
1#
#240000
0#
#241000
1#
#242000
0#
#243000
1#
#244000
0#
#245000
1#
#246000
0#
#247000
1#
#248000
0#
#249000
1#
#250000
0#
#251000
1#
#252000
0#
#253000
1#
#254000
0#
#255000
1#
#256000
0#
#257000
1#
#258000
0#
#259000
1#
#260000
0#
#261000
b101 !
1"
1#
#262000
0#
#263000
b10 ,
1)
b101 -
b1111 (
1#
#264000
0#
#265000
1#
#266000
0#
#267000
1#
#268000
0#
#269000
1#
#270000
0#
#271000
0"
1#
#272000
0#
#273000
b11 ,
0)
1#
#274000
0#
#275000
1#
#276000
0#
#277000
1#
#278000
0#
#279000
1#
#280000
0#
#281000
1#
#282000
0#
#283000
1#
#284000
0#
#285000
1#
#286000
0#
#287000
1#
#288000
0#
#289000
1#
#290000
0#
#291000
1#
#292000
0#
#293000
1#
#294000
0#
#295000
1#
#296000
0#
#297000
1#
#298000
0#
#299000
1#
#300000
0#
#301000
b110 !
1"
1#
#302000
0#
#303000
b10 '
b10 ,
1)
b110 -
b10101 (
1#
#304000
0#
#305000
1#
#306000
0#
#307000
1#
#308000
0#
#309000
1#
#310000
0#
#311000
0"
1#
#312000
0#
#313000
b11 ,
0)
1#
#314000
0#
#315000
1#
#316000
0#
#317000
1#
#318000
0#
#319000
1#
#320000
0#
#321000
1#
#322000
0#
#323000
1#
#324000
0#
#325000
1#
#326000
0#
#327000
1#
#328000
0#
#329000
1#
#330000
0#
#331000
1#
#332000
0#
#333000
1#
#334000
0#
#335000
1#
#336000
0#
#337000
1#
#338000
0#
#339000
1#
#340000
0#
#341000
b111 !
1"
1#
#342000
0#
#343000
b11 '
b10 ,
1)
b111 -
b11100 (
1#
#344000
0#
#345000
1#
#346000
0#
#347000
1#
#348000
0#
#349000
1#
#350000
0#
#351000
0"
1#
#352000
0#
#353000
b11 ,
0)
1#
#354000
0#
#355000
1#
#356000
0#
#357000
1#
#358000
0#
#359000
1#
#360000
0#
#361000
1#
#362000
0#
#363000
1#
#364000
0#
#365000
1#
#366000
0#
#367000
1#
#368000
0#
#369000
1#
#370000
0#
#371000
1#
#372000
0#
#373000
1#
#374000
0#
#375000
1#
#376000
0#
#377000
1#
#378000
0#
#379000
1#
#380000
0#
#381000
b1000 !
1"
1#
#382000
0#
#383000
b100 '
b0 ,
1*
b1000 -
b100100 (
1#
#384000
0#
#385000
1#
#386000
0#
#387000
1#
#388000
0#
#389000
1#
#390000
0#
#391000
1#
#392000
0#
#393000
1#
#394000
0#
#395000
1#
#396000
0#
#397000
1#
#398000
0#
#399000
1#
#400000
0#
#401000
1#
#402000
0#
#403000
1#
#403250
1&
1%
#404000
0#
#405000
b1 ,
b0 -
0&
1+
1#
#406000
0#
#407000
b1 -
1#
#408000
0#
#409000
b10 -
1#
#410000
0#
#411000
b11 -
1#
#412000
0#
#413000
b100 -
1#
#413250
0%
#414000
0#
#415000
0+
b101 -
1#
#416000
0#
#417000
b110 -
1#
#418000
0#
#419000
b111 -
1#
#420000
0#
#421000
b1000 -
1#
#422000
0#
#423000
b1001 -
1#
#424000
0#
#425000
b1010 -
1#
#426000
0#
#427000
b0 '
b0 (
0*
1)
1#
#428000
0#
#429000
b10 ,
b0 -
1#
#430000
0#
#431000
1#
#432000
0#
#433000
1#
#434000
0#
#435000
0"
1#
#436000
0#
#437000
b11 ,
0)
1#
#438000
0#
#439000
1#
#440000
0#
#441000
1#
#442000
0#
#443000
1#
#444000
0#
#445000
1#
#446000
0#
#447000
1#
#448000
0#
#449000
1#
#450000
0#
#451000
1#
#452000
0#
#453000
1#
#454000
0#
#455000
1#
#456000
0#
#457000
1#
#458000
0#
#459000
1#
#460000
0#
#461000
1#
#462000
0#
#463000
1#
#464000
0#
#465000
b111111111111 !
1"
1#
#466000
0#
#467000
b111111111111 '
b10 ,
1)
b1 -
b111111111111111 (
1#
#468000
0#
#469000
1#
#470000
0#
#471000
1#
#472000
0#
#473000
1#
#474000
0#
#475000
0"
1#
#476000
0#
#477000
b11 ,
0)
1#
#478000
0#
#479000
1#
#480000
0#
#481000
1#
#482000
0#
#483000
1#
#484000
0#
#485000
1#
#486000
0#
#487000
1#
#488000
0#
#489000
1#
#490000
0#
#491000
1#
#492000
0#
#493000
1#
#494000
0#
#495000
1#
#496000
0#
#497000
1#
#498000
0#
#499000
1#
#500000
0#
#501000
1#
#502000
0#
#503000
1#
#504000
0#
#505000
1"
1#
#506000
0#
#507000
b10 ,
1)
b10 -
b111111111111110 (
1#
#508000
0#
#509000
1#
#510000
0#
#511000
1#
#512000
0#
#513000
1#
#514000
0#
#515000
0"
1#
#516000
0#
#517000
b11 ,
0)
1#
#518000
0#
#519000
1#
#520000
0#
#521000
1#
#522000
0#
#523000
1#
#524000
0#
#525000
1#
#526000
0#
#527000
1#
#528000
0#
#529000
1#
#530000
0#
#531000
1#
#532000
0#
#533000
1#
#534000
0#
#535000
1#
#536000
0#
#537000
1#
#538000
0#
#539000
1#
#540000
0#
#541000
1#
#542000
0#
#543000
1#
#544000
0#
#545000
1"
1#
#546000
0#
#547000
b10 ,
1)
b11 -
b111111111111101 (
1#
#548000
0#
#549000
1#
#550000
0#
#551000
1#
#552000
0#
#553000
1#
#554000
0#
#555000
0"
1#
#556000
0#
#557000
b11 ,
0)
1#
#558000
0#
#559000
1#
#560000
0#
#561000
1#
#562000
0#
#563000
1#
#564000
0#
#565000
1#
#566000
0#
#567000
1#
#568000
0#
#569000
1#
#570000
0#
#571000
1#
#572000
0#
#573000
1#
#574000
0#
#575000
1#
#576000
0#
#577000
1#
#578000
0#
#579000
1#
#580000
0#
#581000
1#
#582000
0#
#583000
1#
#584000
0#
#585000
1"
1#
#586000
0#
#587000
b10 ,
1)
b100 -
b111111111111100 (
1#
#588000
0#
#589000
1#
#590000
0#
#591000
1#
#592000
0#
#593000
1#
#594000
0#
#595000
0"
1#
#596000
0#
#597000
b11 ,
0)
1#
#598000
0#
#599000
1#
#600000
0#
#601000
1#
#602000
0#
#603000
1#
#604000
0#
#605000
1#
#606000
0#
#607000
1#
#608000
0#
#609000
1#
#610000
0#
#611000
1#
#612000
0#
#613000
1#
#614000
0#
#615000
1#
#616000
0#
#617000
1#
#618000
0#
#619000
1#
#620000
0#
#621000
1#
#622000
0#
#623000
1#
#624000
0#
#625000
1"
1#
#626000
0#
#627000
b10 ,
1)
b101 -
b111111111111011 (
1#
#628000
0#
#629000
1#
#630000
0#
#631000
1#
#632000
0#
#633000
1#
#634000
0#
#635000
0"
1#
#636000
0#
#637000
b11 ,
0)
1#
#638000
0#
#639000
1#
#640000
0#
#641000
1#
#642000
0#
#643000
1#
#644000
0#
#645000
1#
#646000
0#
#647000
1#
#648000
0#
#649000
1#
#650000
0#
#651000
1#
#652000
0#
#653000
1#
#654000
0#
#655000
1#
#656000
0#
#657000
1#
#658000
0#
#659000
1#
#660000
0#
#661000
1#
#662000
0#
#663000
1#
#664000
0#
#665000
1"
1#
#666000
0#
#667000
b10 ,
1)
b110 -
b111111111111010 (
1#
#668000
0#
#669000
1#
#670000
0#
#671000
1#
#672000
0#
#673000
1#
#674000
0#
#675000
0"
1#
#676000
0#
#677000
b11 ,
0)
1#
#678000
0#
#679000
1#
#680000
0#
#681000
1#
#682000
0#
#683000
1#
#684000
0#
#685000
1#
#686000
0#
#687000
1#
#688000
0#
#689000
1#
#690000
0#
#691000
1#
#692000
0#
#693000
1#
#694000
0#
#695000
1#
#696000
0#
#697000
1#
#698000
0#
#699000
1#
#700000
0#
#701000
1#
#702000
0#
#703000
1#
#704000
0#
#705000
1"
1#
#706000
0#
#707000
b10 ,
1)
b111 -
b111111111111001 (
1#
#708000
0#
#709000
1#
#710000
0#
#711000
1#
#712000
0#
#713000
1#
#714000
0#
#715000
0"
1#
#716000
0#
#717000
b11 ,
0)
1#
#718000
0#
#719000
1#
#720000
0#
#721000
1#
#722000
0#
#723000
1#
#724000
0#
#725000
1#
#726000
0#
#727000
1#
#728000
0#
#729000
1#
#730000
0#
#731000
1#
#732000
0#
#733000
1#
#734000
0#
#735000
1#
#736000
0#
#737000
1#
#738000
0#
#739000
1#
#740000
0#
#741000
1#
#742000
0#
#743000
1#
#744000
0#
#745000
1"
1#
#746000
0#
#747000
b0 ,
1*
b1000 -
b111111111111000 (
1#
#748000
0#
#749000
1#
#750000
0#
#751000
1#
#752000
0#
#753000
1#
#754000
0#
#755000
1#
#756000
0#
#757000
1#
#758000
0#
#759000
1#
#760000
0#
#761000
1#
#762000
0#
#763000
1#
#764000
0#
#765000
1#
#766000
0#
#767000
1#
#767250
1&
1%
#768000
0#
#769000
b1 ,
b0 -
0&
1+
1#
#770000
0#
#771000
b1 -
1#
#772000
0#
#773000
b10 -
1#
#774000
0#
#775000
b11 -
1#
#776000
0#
#777000
b100 -
1#
#777250
0%
#778000
0#
#779000
0+
b101 -
1#
#780000
0#
#781000
b110 -
1#
#782000
0#
#783000
b111 -
1#
#784000
0#
#785000
b1000 -
1#
#786000
0#
#787000
b1001 -
1#
#788000
0#
#789000
b1010 -
1#
#790000
0#
#791000
b0 '
b0 (
0*
1)
1#
#792000
0#
#793000
b10 ,
b0 -
1#
#794000
0#
#795000
1#
#796000
0#
#797000
1#
#798000
0#
#799000
0"
1#
#800000
0#
#801000
b11 ,
0)
1#
#802000
0#
#803000
1#
#804000
0#
#805000
1#
#806000
0#
#807000
1#
#808000
0#
#809000
1#
#810000
0#
#811000
1#
#812000
0#
#813000
1#
#814000
0#
#815000
1#
#816000
0#
#817000
1#
#818000
0#
#819000
1#
#820000
0#
#821000
1#
#822000
0#
#823000
1#
#824000
0#
#825000
1#
#826000
0#
#827000
1#
#828000
0#
#829000
b1011100 !
1"
1#
#830000
0#
#831000
b1011 '
b10 ,
1)
b1 -
b1011100 (
1#
#832000
0#
#833000
1#
#834000
0#
#835000
1#
#836000
0#
#837000
1#
#838000
0#
#839000
0"
1#
#840000
0#
#841000
b11 ,
0)
1#
#842000
0#
#843000
1#
#844000
0#
#845000
1#
#846000
0#
#847000
1#
#848000
0#
#849000
1#
#850000
0#
#851000
1#
#852000
0#
#853000
1#
#854000
0#
#855000
1#
#856000
0#
#857000
1#
#858000
0#
#859000
1#
#860000
0#
#861000
1#
#862000
0#
#863000
1#
#864000
0#
#865000
1#
#866000
0#
#867000
1#
#868000
0#
#869000
b1000001 !
1"
1#
#870000
0#
#871000
b10011 '
b10 ,
1)
b10 -
b10011101 (
1#
#872000
0#
#873000
1#
#874000
0#
#875000
1#
#876000
0#
#877000
1#
#878000
0#
#879000
0"
1#
#880000
0#
#881000
b11 ,
0)
1#
#882000
0#
#883000
1#
#884000
0#
#885000
1#
#886000
0#
#887000
1#
#888000
0#
#889000
1#
#890000
0#
#891000
1#
#892000
0#
#893000
1#
#894000
0#
#895000
1#
#896000
0#
#897000
1#
#898000
0#
#899000
1#
#900000
0#
#901000
1#
#902000
0#
#903000
1#
#904000
0#
#905000
1#
#906000
0#
#907000
1#
#908000
0#
#909000
b100 !
1"
1#
#910000
0#
#911000
b10100 '
b10 ,
1)
b11 -
b10100001 (
1#
#912000
0#
#913000
1#
#914000
0#
#915000
1#
#916000
0#
#917000
1#
#918000
0#
#919000
0"
1#
#920000
0#
#921000
b11 ,
0)
1#
#922000
0#
#923000
1#
#924000
0#
#925000
1#
#926000
0#
#927000
1#
#928000
0#
#929000
1#
#930000
0#
#931000
1#
#932000
0#
#933000
1#
#934000
0#
#935000
1#
#936000
0#
#937000
1#
#938000
0#
#939000
1#
#940000
0#
#941000
1#
#942000
0#
#943000
1#
#944000
0#
#945000
1#
#946000
0#
#947000
1#
#948000
0#
#949000
b11011110 !
1"
1#
#950000
0#
#951000
b101111 '
b10 ,
1)
b100 -
b101111111 (
1#
#952000
0#
#953000
1#
#954000
0#
#955000
1#
#956000
0#
#957000
1#
#958000
0#
#959000
0"
1#
#960000
0#
#961000
b11 ,
0)
1#
#962000
0#
#963000
1#
#964000
0#
#965000
1#
#966000
0#
#967000
1#
#968000
0#
#969000
1#
#970000
0#
#971000
1#
#972000
0#
#973000
1#
#974000
0#
#975000
1#
#976000
0#
#977000
1#
#978000
0#
#979000
1#
#980000
0#
#981000
1#
#982000
0#
#983000
1#
#984000
0#
#985000
1#
#986000
0#
#987000
1#
#988000
0#
#989000
b0 !
1"
1#
#990000
0#
#991000
b10 ,
1)
b101 -
1#
#992000
0#
#993000
1#
#994000
0#
#995000
1#
#996000
0#
#997000
1#
#998000
0#
#999000
0"
1#
#1000000
0#
#1001000
b11 ,
0)
1#
#1002000
0#
#1003000
1#
#1004000
0#
#1005000
1#
#1006000
0#
#1007000
1#
#1008000
0#
#1009000
1#
#1010000
0#
#1011000
1#
#1012000
0#
#1013000
1#
#1014000
0#
#1015000
1#
#1016000
0#
#1017000
1#
#1018000
0#
#1019000
1#
#1020000
0#
#1021000
1#
#1022000
0#
#1023000
1#
#1024000
0#
#1025000
1#
#1026000
0#
#1027000
1#
#1028000
0#
#1029000
b111110110011 !
1"
1#
#1030000
0#
#1031000
b100110 '
b10 ,
1)
b110 -
b100110010 (
1#
#1032000
0#
#1033000
1#
#1034000
0#
#1035000
1#
#1036000
0#
#1037000
1#
#1038000
0#
#1039000
0"
1#
#1040000
0#
#1041000
b11 ,
0)
1#
#1042000
0#
#1043000
1#
#1044000
0#
#1045000
1#
#1046000
0#
#1047000
1#
#1048000
0#
#1049000
1#
#1050000
0#
#1051000
1#
#1052000
0#
#1053000
1#
#1054000
0#
#1055000
1#
#1056000
0#
#1057000
1#
#1058000
0#
#1059000
1#
#1060000
0#
#1061000
1#
#1062000
0#
#1063000
1#
#1064000
0#
#1065000
1#
#1066000
0#
#1067000
1#
#1068000
0#
#1069000
b1100 !
1"
1#
#1070000
0#
#1071000
b100111 '
b10 ,
1)
b111 -
b100111110 (
1#
#1072000
0#
#1073000
1#
#1074000
0#
#1075000
1#
#1076000
0#
#1077000
1#
#1078000
0#
#1079000
0"
1#
#1080000
0#
#1081000
b11 ,
0)
1#
#1082000
0#
#1083000
1#
#1084000
0#
#1085000
1#
#1086000
0#
#1087000
1#
#1088000
0#
#1089000
1#
#1090000
0#
#1091000
1#
#1092000
0#
#1093000
1#
#1094000
0#
#1095000
1#
#1096000
0#
#1097000
1#
#1098000
0#
#1099000
1#
#1100000
0#
#1101000
1#
#1102000
0#
#1103000
1#
#1104000
0#
#1105000
1#
#1106000
0#
#1107000
1#
#1108000
0#
#1109000
b11 !
1"
1#
#1110000
0#
#1111000
b101000 '
b0 ,
1*
b1000 -
b101000001 (
1#
#1112000
0#
#1113000
1#
#1114000
0#
#1115000
1#
#1116000
0#
#1117000
1#
#1118000
0#
#1119000
1#
#1120000
0#
#1121000
1#
#1122000
0#
#1123000
1#
#1124000
0#
#1125000
1#
#1126000
0#
#1127000
1#
#1128000
0#
#1129000
1#
#1130000
0#
#1131000
1#
#1131250
1&
1%
#1132000
0#
#1133000
b1 ,
b0 -
0&
1+
1#
#1134000
0#
#1135000
b1 -
1#
#1136000
0#
#1137000
b10 -
1#
#1138000
0#
#1139000
b11 -
1#
#1140000
0#
#1141000
b100 -
1#
#1141250
0%
#1142000
0#
#1143000
0+
b101 -
1#
#1144000
0#
#1145000
b110 -
1#
#1146000
0#
#1147000
b111 -
1#
#1148000
0#
#1149000
b1000 -
1#
#1150000
0#
#1151000
b1001 -
1#
#1152000
0#
#1153000
b1010 -
1#
#1154000
0#
#1155000
b0 '
b0 (
0*
1)
1#
#1156000
0#
#1157000
b10 ,
b0 -
1#
#1158000
0#
#1159000
1#
#1160000
0#
#1161000
1#
#1162000
0#
#1163000
0"
1#
#1164000
0#
#1165000
b11 ,
0)
1#
#1166000
0#
#1167000
1#
#1168000
0#
#1169000
1#
#1170000
0#
#1171000
1#
#1172000
0#
#1173000
1#
#1174000
0#
#1175000
1#
#1176000
0#
#1177000
1#
#1178000
0#
#1179000
1#
#1180000
0#
#1181000
1#
#1182000
0#
#1183000
1#
#1184000
0#
#1185000
1#
#1186000
0#
#1187000
1#
#1188000
0#
#1189000
1#
#1190000
0#
#1191000
1#
#1192000
0#
#1193000
b110110111000 !
1"
1#
#1194000
0#
#1195000
b111110110111 '
b10 ,
1)
b1 -
b111110110111000 (
1#
#1196000
0#
#1197000
1#
#1198000
0#
#1199000
1#
#1200000
0#
#1201000
1#
#1202000
0#
#1203000
0"
1#
#1204000
0#
#1205000
b11 ,
0)
1#
#1206000
0#
#1207000
1#
#1208000
0#
#1209000
1#
#1210000
0#
#1211000
1#
#1212000
0#
#1213000
1#
#1214000
0#
#1215000
1#
#1216000
0#
#1217000
1#
#1218000
0#
#1219000
1#
#1220000
0#
#1221000
1#
#1222000
0#
#1223000
1#
#1224000
0#
#1225000
1#
#1226000
0#
#1227000
1#
#1228000
0#
#1229000
1#
#1230000
0#
#1231000
1#
#1232000
0#
#1233000
b110000101101 !
1"
1#
#1234000
0#
#1235000
b111100111100 '
b10 ,
1)
b10 -
b111100111100101 (
1#
#1236000
0#
#1237000
1#
#1238000
0#
#1239000
1#
#1240000
0#
#1241000
1#
#1242000
0#
#1243000
0"
1#
#1244000
0#
#1245000
b11 ,
0)
1#
#1246000
0#
#1247000
1#
#1248000
0#
#1249000
1#
#1250000
0#
#1251000
1#
#1252000
0#
#1253000
1#
#1254000
0#
#1255000
1#
#1256000
0#
#1257000
1#
#1258000
0#
#1259000
1#
#1260000
0#
#1261000
1#
#1262000
0#
#1263000
1#
#1264000
0#
#1265000
1#
#1266000
0#
#1267000
1#
#1268000
0#
#1269000
1#
#1270000
0#
#1271000
1#
#1272000
0#
#1273000
b101000111010 !
1"
1#
#1274000
0#
#1275000
b111010000011 '
b10 ,
1)
b11 -
b111010000011111 (
1#
#1276000
0#
#1277000
1#
#1278000
0#
#1279000
1#
#1280000
0#
#1281000
1#
#1282000
0#
#1283000
0"
1#
#1284000
0#
#1285000
b11 ,
0)
1#
#1286000
0#
#1287000
1#
#1288000
0#
#1289000
1#
#1290000
0#
#1291000
1#
#1292000
0#
#1293000
1#
#1294000
0#
#1295000
1#
#1296000
0#
#1297000
1#
#1298000
0#
#1299000
1#
#1300000
0#
#1301000
1#
